Metadata-Version: 2.1
Name: df-data-validator
Version: 0.0.1
Summary: Data Validation package
Author: Shrishty
